analytics/__init__.py
analytics/admin.py
analytics/apps.py
analytics/forms.py
analytics/models.py
analytics/urls.py
analytics/views.py
analytics/management/commands/analytics_set.py
analytics/management/commands/update_analyticsdata.py
analytics/migrations/0001_initial.py
analytics/migrations/0002_auto_20240229_1302.py
analytics/migrations/0003_googleanalytics4config.py
analytics/migrations/0004_auto_20240304_1746.py
analytics/migrations/0005_analyticsappsettings.py
analytics/migrations/0006_analyticsappsettings_base_html_file.py
analytics/migrations/0007_auto_20240309_1826.py
analytics/migrations/0008_auto_20240309_2054.py
analytics/migrations/0009_auto_20240309_2305.py
analytics/migrations/0010_auto_20240310_1937.py
analytics/migrations/0011_auto_20240313_1210.py
analytics/migrations/0012_auto_20240316_0936.py
analytics/migrations/0013_auto_20240316_1346.py
analytics/migrations/0014_auto_20240317_1705.py
analytics/migrations/0015_googleanalytics4config_credential_path.py
analytics/migrations/__init__.py
analytics/safety/function.py
analytics/static/analytics/css/style.css
analytics/templates/analytics/base_index.html
analytics/templates/analytics/include_index.html
analytics/templates/analytics/include_nav_message_modal.html
analytics/templates/analytics/include_not_analytics_set.html
analytics/templates/analytics/index.html
analytics/tests/__init__.py
analytics/tests/test_admin.py
analytics/tests/test_forms.py
analytics/tests/test_models.py
analytics/tests/test_safety.py
analytics/tests/test_views.py
analytics/update_api/ga4_api.py
analytics/update_api/update_data.py
zfl_analytics-0.0.7a0.dist-info/METADATA
zfl_analytics-0.0.7a0.dist-info/WHEEL
zfl_analytics-0.0.7a0.dist-info/licenses/LICENSE.txt
zfl_analytics-0.0.7a0.dist-info/RECORD
