Metadata-Version: 2.1
Name: zfl-analytics
Version: 0.0.7a0
Project-URL: Documentation, https://github.com/unknown/analytics#readme
Project-URL: Issues, https://github.com/unknown/analytics/issues
Project-URL: Source, https://github.com/unknown/analytics
Author-email: You are name <example@gmail.com>
License-Expression: MIT
License-File: LICENSE.txt
Classifier: Development Status :: 4 - Beta
Classifier: Environment :: Web Environment
Classifier: Framework :: Django
Classifier: Intended Audience :: Developers
Classifier: Programming Language :: Python
Classifier: Programming Language :: Python :: 3.6
Classifier: Programming Language :: Python :: Implementation :: CPython
Classifier: Programming Language :: Python :: Implementation :: PyPy
Requires-Python: >=3.6
Requires-Dist: django-pandas==0.6.6
Requires-Dist: django==2.2.5
Requires-Dist: google-analytics-data==0.12.1
